presentpy/__init__.py
presentpy/__main__.py
presentpy/code_slide_source.py
presentpy/constants.py
presentpy/namespaces.py
presentpy/readers/__init__.py
presentpy/readers/notebook.py
presentpy/templates/__init__.py
presentpy/templates/content.py
presentpy/templates/manifest.py
presentpy/templates/odp/META-INF/manifest.xml
presentpy/templates/odp/content.xml
presentpy/templates/odp/meta.xml
presentpy/templates/odp/mimetype
presentpy/templates/odp/settings.xml
presentpy/templates/odp/styles.xml
presentpy/templates/styles.py
presentpy/templates/xml_file.py
presentpy/writer/__init__.py
presentpy/writer/presentation.py
presentpy/writer/slide_tag.py
presentpy/writer/slides.py
presentpy/writer/tag.py
presentpy/writer/theme.py
presentpy-1.4.6.dist-info/METADATA
presentpy-1.4.6.dist-info/WHEEL
presentpy-1.4.6.dist-info/entry_points.txt
presentpy-1.4.6.dist-info/RECORD
