Metadata-Version: 2.1
Name: presentpy
Version: 1.4.6
Summary: Create slides from Jupyter Notebooks
License: MIT
Author: Antonio Feregrino
Author-email: antonio.feregrino@gmail.com
Requires-Python: >=3.10,<4.0
Classifier: License :: OSI Approved :: MIT License
Classifier: Programming Language :: Python :: 3
Classifier: Programming Language :: Python :: 3.10
Classifier: Programming Language :: Python :: 3.11
Requires-Dist: beautifulsoup4 (>=4.12.3,<5.0.0)
Requires-Dist: click (>=8.1.7,<9.0.0)
Requires-Dist: colour (>=0.1.5,<0.2.0)
Requires-Dist: lxml (>=5.2.2,<6.0.0)
Requires-Dist: mistletoe (>=1.4.0,<2.0.0)
Requires-Dist: nbformat (>=5.10.4,<6.0.0)
Requires-Dist: pillow (>=10.4.0,<11.0.0)
Requires-Dist: pygments (>=2.18.0,<3.0.0)
